qreward/__init__.py
qreward/_version.py
qreward/globals.py
qreward/types.py
qreward/client/__init__.py
qreward/client/openai.py
qreward/client/patch_openai.py
qreward/utils/__init__.py
qreward/utils/patch.py
qreward/utils/retry.py
qreward/utils/schedule.py
qreward/utils/socket_keepalive.py
tests/__init__.py
tests/test_openai_proxy.py
tests/test_patch.py
tests/test_patch_openai.py
tests/test_retry.py
tests/test_schedule.py
tests/test_socket_keepalive.py
qreward-0.1.6.dist-info/METADATA
qreward-0.1.6.dist-info/WHEEL
qreward-0.1.6.dist-info/top_level.txt
qreward-0.1.6.dist-info/RECORD
