Metadata-Version: 2.1
Name: qreward
Version: 0.1.6
Summary: RewardService Python Client, make RL Training reward function easier
Home-page: https://github.com/AQ-MedAI/QReward
Author: sunhailin-Leo
Author-email: 379978424@qq.com
Maintainer: sunhailin-Leo
Maintainer-email: 379978424@qq.com
License: LEGAL.md
Keywords: Reward,RL,Reinforcement Learning,Reward Service
Platform: UNKNOWN
Classifier: Development Status :: 5 - Production/Stable
Classifier: Environment :: Console
Classifier: Intended Audience :: Developers
Classifier: Intended Audience :: Information Technology
Classifier: Intended Audience :: System Administrators
Classifier: Operating System :: MacOS
Classifier: Operating System :: POSIX :: Linux
Classifier: Operating System :: Unix
Classifier: Programming Language :: Python
Classifier: Programming Language :: Python :: 3.10
Classifier: Programming Language :: Python :: 3.11
Classifier: Programming Language :: Python :: 3.12
Classifier: Programming Language :: Python :: 3.13
Classifier: Programming Language :: Python :: 3.14
Classifier: Topic :: Software Development :: Libraries :: Python Modules
Classifier: Topic :: Utilities
Classifier: Typing :: Typed
Requires-Dist: openai
Requires-Dist: aiohttp
Requires-Dist: httpx-aiohttp
Requires-Dist: httpx
Requires-Dist: aiodns
Requires-Dist: tenacity
Requires-Dist: aiolimiter
Requires-Dist: requests
